rata/__init__.py
rata/__main__.py
rata/libs/__init__.py
rata/libs/application.py
rata/libs/edit_tasks.py
rata/libs/exceptions.py
rata/libs/io.py
rata/libs/tasks.py
rata/libs/widgets.py
rata-1.0.0.dist-info/licenses/LICENSE
rata-1.0.0.dist-info/METADATA
rata-1.0.0.dist-info/WHEEL
rata-1.0.0.dist-info/entry_points.txt
rata-1.0.0.dist-info/top_level.txt
rata-1.0.0.dist-info/RECORD
